[{"label":"JAN","costs":[{"capacity":0,"cost":2.35999989509583},{"capacity":118,"cost":0}]},{"label":"FEB","costs":[{"capacity":0,"cost":2.35999989509583},{"capacity":118,"cost":0}]},{"label":"MAR","costs":[{"capacity":0,"cost":2.55999994277954},{"capacity":128,"cost":0}]},{"label":"APR","costs":[{"capacity":0,"cost":2.83999991416931},{"capacity":142,"cost":0}]},{"label":"MAY","costs":[{"capacity":0,"cost":3},{"capacity":150,"cost":0}]},{"label":"JUN","costs":[{"capacity":0,"cost":3},{"capacity":150,"cost":0}]},{"label":"JUL","costs":[{"capacity":0,"cost":3},{"capacity":150,"cost":0}]},{"label":"AUG","costs":[{"capacity":0,"cost":3},{"capacity":150,"cost":0}]},{"label":"SEP","costs":[{"capacity":0,"cost":2.70000004768372},{"capacity":135,"cost":0}]},{"label":"OCT","costs":[{"capacity":0,"cost":2.40000009536743},{"capacity":120,"cost":0}]},{"label":"NOV","costs":[{"capacity":0,"cost":2.09999990463257},{"capacity":105,"cost":0}]},{"label":"DEC","costs":[{"capacity":0,"cost":2.14000010490417},{"capacity":107,"cost":0}]}]